{"presente":{"eu":"cedo","tu":"cedes","ele":"cede","nos":"cedemos","vos":"cedeis","eles":"cedem"},"preterito_imperfeito":{"eu":"cedia","tu":"cedias","ele":"cedia","nos":"cedíamos","vos":"cedíeis","eles":"cediam"},"preterito_perfeito":{"eu":"cedi","tu":"cedeste","ele":"cedeu","nos":"cedemos","vos":"cedestes","eles":"cederam"},"preterito_mais_que_perfeito":{"eu":"cedera","tu":"cederas","ele":"cedera","nos":"cedêramos","vos":"cedêreis","eles":"cederam"},"futuro_do_presente":{"eu":"cederei","tu":"cederás","ele":"cederá","nos":"cederemos","vos":"cedereis","eles":"cederão"},"futuro_do_preterito":{"eu":"cederia","tu":"cederias","ele":"cederia","nos":"cederíamos","vos":"cederíeis","eles":"cederiam"}}