{"presente":{"eu":"chefio","tu":"chefias","ele":"chefia","nos":"chefiamos","vos":"chefiais","eles":"chefiam"},"preterito_imperfeito":{"eu":"chefiava","tu":"chefiavas","ele":"chefiava","nos":"chefiávamos","vos":"chefiáveis","eles":"chefiavam"},"preterito_perfeito":{"eu":"chefiei","tu":"chefiaste","ele":"chefiou","nos":"chefiamos","vos":"chefiastes","eles":"chefiaram"},"preterito_mais_que_perfeito":{"eu":"chefiara","tu":"chefiaras","ele":"chefiara","nos":"chefiáramos","vos":"chefiáreis","eles":"chefiaram"},"futuro_do_presente":{"eu":"chefiarei","tu":"chefiarás","ele":"chefiará","nos":"chefiaremos","vos":"chefiareis","eles":"chefiarão"},"futuro_do_preterito":{"eu":"chefiaria","tu":"chefiarias","ele":"chefiaria","nos":"chefiaríamos","vos":"chefiaríeis","eles":"chefiariam"}}