{"presente":{"eu":"contrato","tu":"contratas","ele":"contrata","nos":"contratamos","vos":"contratais","eles":"contratam"},"preterito_imperfeito":{"eu":"contratava","tu":"contratavas","ele":"contratava","nos":"contratávamos","vos":"contratáveis","eles":"contratavam"},"preterito_perfeito":{"eu":"contratei","tu":"contrataste","ele":"contratou","nos":"contratamos","vos":"contratastes","eles":"contrataram"},"preterito_mais_que_perfeito":{"eu":"contratara","tu":"contrataras","ele":"contratara","nos":"contratáramos","vos":"contratáreis","eles":"contrataram"},"futuro_do_presente":{"eu":"contratarei","tu":"contratarás","ele":"contratará","nos":"contrataremos","vos":"contratareis","eles":"contratarão"},"futuro_do_preterito":{"eu":"contrataria","tu":"contratarias","ele":"contrataria","nos":"contrataríamos","vos":"contrataríeis","eles":"contratariam"}}