{"presente":{"eu":"creio","tu":"crês","ele":"crê","nos":"cremos","vos":"credes","eles":"creem"},"preterito_imperfeito":{"eu":"cria","tu":"crias","ele":"cria","nos":"críamos","vos":"críeis","eles":"criam"},"preterito_perfeito":{"eu":"cri","tu":"creste","ele":"creu","nos":"cremos","vos":"crestes","eles":"creram"},"preterito_mais_que_perfeito":{"eu":"crera","tu":"creras","ele":"crera","nos":"crêramos","vos":"crêreis","eles":"creram"},"futuro_do_presente":{"eu":"crerei","tu":"crerás","ele":"crerá","nos":"creremos","vos":"crereis","eles":"crerão"},"futuro_do_preterito":{"eu":"creria","tu":"crerias","ele":"creria","nos":"creríamos","vos":"creríeis","eles":"creriam"}}