{"presente":{"eu":"dedico","tu":"dedicas","ele":"dedica","nos":"dedicamos","vos":"dedicais","eles":"dedicam"},"preterito_imperfeito":{"eu":"dedicava","tu":"dedicavas","ele":"dedicava","nos":"dedicávamos","vos":"dedicáveis","eles":"dedicavam"},"preterito_perfeito":{"eu":"dediquei","tu":"dedicaste","ele":"dedicou","nos":"dedicamos","vos":"dedicastes","eles":"dedicaram"},"preterito_mais_que_perfeito":{"eu":"dedicara","tu":"dedicaras","ele":"dedicara","nos":"dedicáramos","vos":"dedicáreis","eles":"dedicaram"},"futuro_do_presente":{"eu":"dedicarei","tu":"dedicarás","ele":"dedicará","nos":"dedicaremos","vos":"dedicareis","eles":"dedicarão"},"futuro_do_preterito":{"eu":"dedicaria","tu":"dedicarias","ele":"dedicaria","nos":"dedicaríamos","vos":"dedicaríeis","eles":"dedicariam"}}