{"presente":{"eu":"desisto","tu":"desistes","ele":"desiste","nos":"desistimos","vos":"desistis","eles":"desistem"},"preterito_imperfeito":{"eu":"desistia","tu":"desistias","ele":"desistia","nos":"desistíamos","vos":"desistíeis","eles":"desistiam"},"preterito_perfeito":{"eu":"desisti","tu":"desististe","ele":"desistiu","nos":"desistimos","vos":"desististes","eles":"desistiram"},"preterito_mais_que_perfeito":{"eu":"desistira","tu":"desistiras","ele":"desistira","nos":"desistíramos","vos":"desistíreis","eles":"desistiram"},"futuro_do_presente":{"eu":"desistirei","tu":"desistirás","ele":"desistirá","nos":"desistiremos","vos":"desistireis","eles":"desistirão"},"futuro_do_preterito":{"eu":"desistiria","tu":"desistirias","ele":"desistiria","nos":"desistiríamos","vos":"desistiríeis","eles":"desistiriam"}}