{"presente":{"eu":"pressiono","tu":"pressionas","ele":"pressiona","nos":"pressionamos","vos":"pressionais","eles":"pressionam"},"preterito_imperfeito":{"eu":"pressionava","tu":"pressionavas","ele":"pressionava","nos":"pressionávamos","vos":"pressionáveis","eles":"pressionavam"},"preterito_perfeito":{"eu":"pressionei","tu":"pressionaste","ele":"pressionou","nos":"pressionamos","vos":"pressionastes","eles":"pressionaram"},"preterito_mais_que_perfeito":{"eu":"pressionara","tu":"pressionaras","ele":"pressionara","nos":"pressionáramos","vos":"pressionáreis","eles":"pressionaram"},"futuro_do_presente":{"eu":"pressionarei","tu":"pressionarás","ele":"pressionará","nos":"pressionaremos","vos":"pressionareis","eles":"pressionarão"},"futuro_do_preterito":{"eu":"pressionaria","tu":"pressionarias","ele":"pressionaria","nos":"pressionaríamos","vos":"pressionaríeis","eles":"pressionariam"}}