{"presente":{"eu":"resgato","tu":"resgatas","ele":"resgata","nos":"resgatamos","vos":"resgatais","eles":"resgatam"},"preterito_imperfeito":{"eu":"resgatava","tu":"resgatavas","ele":"resgatava","nos":"resgatávamos","vos":"resgatáveis","eles":"resgatavam"},"preterito_perfeito":{"eu":"resgatei","tu":"resgataste","ele":"resgatou","nos":"resgatamos","vos":"resgatastes","eles":"resgataram"},"preterito_mais_que_perfeito":{"eu":"resgatara","tu":"resgataras","ele":"resgatara","nos":"resgatáramos","vos":"resgatáreis","eles":"resgataram"},"futuro_do_presente":{"eu":"resgatarei","tu":"resgatarás","ele":"resgatará","nos":"resgataremos","vos":"resgatareis","eles":"resgatarão"},"futuro_do_preterito":{"eu":"resgataria","tu":"resgatarias","ele":"resgataria","nos":"resgataríamos","vos":"resgataríeis","eles":"resgatariam"}}