{"presente":{"eu":"restauro","tu":"restauras","ele":"restaura","nos":"restauramos","vos":"restaurais","eles":"restauram"},"preterito_imperfeito":{"eu":"restaurava","tu":"restauravas","ele":"restaurava","nos":"restaurávamos","vos":"restauráveis","eles":"restauravam"},"preterito_perfeito":{"eu":"restaurei","tu":"restauraste","ele":"restaurou","nos":"restauramos","vos":"restaurastes","eles":"restauraram"},"preterito_mais_que_perfeito":{"eu":"restaurara","tu":"restauraras","ele":"restaurara","nos":"restauráramos","vos":"restauráreis","eles":"restauraram"},"futuro_do_presente":{"eu":"restaurarei","tu":"restaurarás","ele":"restaurará","nos":"restauraremos","vos":"restaurareis","eles":"restaurarão"},"futuro_do_preterito":{"eu":"restauraria","tu":"restaurarias","ele":"restauraria","nos":"restauraríamos","vos":"restauraríeis","eles":"restaurariam"}}