{"presente":{"eu":"revejo","tu":"revês","ele":"revê","nos":"revemos","vos":"revedes","eles":"reveem"},"preterito_imperfeito":{"eu":"revia","tu":"revias","ele":"revia","nos":"revíamos","vos":"revíeis","eles":"reviam"},"preterito_perfeito":{"eu":"revi","tu":"reviste","ele":"reviu","nos":"revimos","vos":"revistes","eles":"reviram"},"preterito_mais_que_perfeito":{"eu":"revira","tu":"reviras","ele":"revira","nos":"revíramos","vos":"revíreis","eles":"reviram"},"futuro_do_presente":{"eu":"reverei","tu":"reverás","ele":"reverá","nos":"reveremos","vos":"revereis","eles":"reverão"},"futuro_do_preterito":{"eu":"reveria","tu":"reverias","ele":"reveria","nos":"reveríamos","vos":"reveríeis","eles":"reveriam"}}