{"presente":{"eu":"vendo","tu":"vendes","ele":"vende","nos":"vendemos","vos":"vendeis","eles":"vendem"},"preterito_imperfeito":{"eu":"vendia","tu":"vendias","ele":"vendia","nos":"vendíamos","vos":"vendíeis","eles":"vendiam"},"preterito_perfeito":{"eu":"vendi","tu":"vendeste","ele":"vendeu","nos":"vendemos","vos":"vendestes","eles":"venderam"},"preterito_mais_que_perfeito":{"eu":"vendera","tu":"venderas","ele":"vendera","nos":"vendêramos","vos":"vendêreis","eles":"venderam"},"futuro_do_presente":{"eu":"venderei","tu":"venderás","ele":"venderá","nos":"venderemos","vos":"vendereis","eles":"venderão"},"futuro_do_preterito":{"eu":"venderia","tu":"venderias","ele":"venderia","nos":"venderíamos","vos":"venderíeis","eles":"venderiam"}}