{"presente":{"eu":"verifico","tu":"verificas","ele":"verifica","nos":"verificamos","vos":"verificais","eles":"verificam"},"preterito_imperfeito":{"eu":"verificava","tu":"verificavas","ele":"verificava","nos":"verificávamos","vos":"verificáveis","eles":"verificavam"},"preterito_perfeito":{"eu":"verifiquei","tu":"verificaste","ele":"verificou","nos":"verificamos","vos":"verificastes","eles":"verificaram"},"preterito_mais_que_perfeito":{"eu":"verificara","tu":"verificaras","ele":"verificara","nos":"verificáramos","vos":"verificáreis","eles":"verificaram"},"futuro_do_presente":{"eu":"verificarei","tu":"verificarás","ele":"verificará","nos":"verificaremos","vos":"verificareis","eles":"verificarão"},"futuro_do_preterito":{"eu":"verificaria","tu":"verificarias","ele":"verificaria","nos":"verificaríamos","vos":"verificaríeis","eles":"verificariam"}}